{"streicheln": 0, "freiheit": 1, "gesundheit": 2, "liebe": 3, "frieden": 4, "freude": 5, "freund": 6, "himmel": 7, "loyal": 8, "vergnuegen": 9, "sanft": 10, "ehrlich": 11, "gluecklich": 12, "diplom": 13, "geschenk": 14, "ehre": 15, "wunder": 16, "familie": 17, "lachen": 18, "paradies": 19, "ferien": 20, "missbrauch": 21, "absturz": 22, "schmutz": 23, "mord": 24, "krankheit": 25, "tod": 26, "trauer": 27, "vergiften": 28, "stinken": 29, "angriff": 30, "katastrophe": 31, "hass": 32, "verschmutzen": 33, "tragoedie": 34, "scheidung": 35, "gefaengnis": 36, "armut": 37, "haesslich": 38, "krebs": 39, "toeten": 40, "faul": 41, "erbrechen": 42, "qual": 43, "geben": 44, "selbstlos": 45, "uneigennuetzig": 46, "sparsam": 47, "proletariat": 48, "industriearbeiter": 49, "nehmen": 50, "gier": 51, "gierig": 52, "egoistisch": 53, "eigennuetzig": 54, "verschwenderisch": 55, "bourgeoisie": 56, "wohlstand": 57, "bankier": 58, "wucher": 59, "kamerad": 60, "ehrlichkeit": 61, "ersichtlich": 62, "aufrichtig": 63, "vertrauenswuerdig": 64, "wahr": 65, "unschuldig": 66, "freundschaftlich": 67, "hell": 68, "zugaenglich": 69, "machtlos": 70, "ohnmacht": 71, "untertan": 72, "spitzel": 73, "verrat": 74, "geheim": 75, "betruegerisch": 76, "unwahr": 77, "zweifelhaft": 78, "verbrecher": 79, "bedrohlich": 80, "dunkel": 81, "geheimnis": 82, "einflussreich": 83, "weltmacht": 84, "herrschaft": 85, "verschwoerung": 86, "glaeubige": 87, "geistlich": 88, "engel": 89, "heilig": 90, "fromm": 91, "goettlich": 92, "ehrwuerdig": 93, "treu": 94, "glaeubig": 95, "religioes": 96, "weltlich": 97, "teufel": 98, "irdisch": 99, "atheistisch": 100, "verflucht": 101, "untreu": 102, "unglaeubig": 103, "gotteslaesterung": 104, "normal": 105, "ueberlegenheit": 106, "gleichheit": 107, "angenehm": 108, "freundlich": 109, "ehrenwert": 110, "sympathie": 111, "akzeptiert": 112, "besser": 113, "national": 114, "rein": 115, "ueberlegen": 116, "sauber": 117, "ehrenhaft": 118, "seltsam": 119, "unterlegenheit": 120, "ungleichheit": 121, "unangenehm": 122, "boshaft": 123, "schaendlich": 124, "abgelehnt": 125, "schlechter": 126, "unterlegen": 127, "schmutzig": 128, "verseucht": 129, "schaedlich": 130, "niedertraechtig": 131, "bescheiden": 132, "sittlich": 133, "anstaendig": 134, "wuerdig": 135, "moralisch": 136, "gesittet": 137, "gewissenhaft": 138, "vorbildlich": 139, "unbescheiden": 140, "unsittlich": 141, "unanstaendig": 142, "korrupt": 143, "unwuerdig": 144, "unmoralisch": 145, "unehrlich": 146, "verdorben": 147, "gewissenlos": 148, "barbarisch": 149, "patriotisch": 150, "vaterlandsliebe": 151, "germanisch": 152, "nationalbewusstsein": 153, "vaterlaendisch": 154, "nationalgefuehl": 155, "volkstum": 156, "patriotismus": 157, "patriot": 158, "nichtdeutsch": 159, "vaterlandslos": 160, "antideutsch": 161, "heimatlos": 162, "separatistisch": 163, "staatsfeindlich": 164, "fremd": 165, "dissident": 166, "judentum": 167, "jude": 168, "juedisch": 169, "israel": 170, "israelisch": 171, "synagoge": 172, "orthodox": 173, "zentralrat": 174, "christ": 175, "christlich": 176, "christentum": 177, "evangelisch": 178, "evangelium": 179, "jesus": 180, "katholisch": 181, "kirche": 182, "pfarrer": 183, "taufe": 184, "abendland": 185, "protestant": 186, "protestantisch": 187, "landeskirche": 188, "kirchentag": 189, "ekd": 190, "landesbischof": 191, "lutherisch": 192, "diakonie": 193, "katholik": 194, "papst": 195, "enzyklika": 196, "paepstlich": 197, "bischofskonferenz": 198}